Testthu/__init__.py
Testthu/demo.py
Testthu-1.0.1.dist-info/LICENSE
Testthu-1.0.1.dist-info/METADATA
Testthu-1.0.1.dist-info/WHEEL
Testthu-1.0.1.dist-info/top_level.txt
Testthu-1.0.1.dist-info/RECORD
