Metadata-Version: 2.1
Name: Testthu
Version: 1.0.1
Summary: thu
Home-page: https://github.com/huynhquoc1990/Testthu.git
Author: Quoc
Author-email: huynhquoc1990@gmail.com
License: MIT
Platform: UNKNOWN
